bouquet/__init__.py
bouquet/bouquet.py
bouquet/compose.py
bouquet/defaults.py
bouquet/models.py
bouquet/services/__init__.py
bouquet/services/types/__init__.py
bouquet/services/types/bluesky_blissdata.py
bouquet/services/types/callback_handler.py
bouquet/services/types/daiquiri_bluesky.py
bouquet/services/types/document_proxy.py
bouquet/services/types/flint.py
bouquet/services/types/jupyterhub.py
bouquet/services/types/mariadb.py
bouquet/services/types/mongodb.py
bouquet/services/types/queueserver.py
bouquet/services/types/queueserver_http_api.py
bouquet/services/types/queueserver_qtgui.py
bouquet/services/types/redis.py
bouquet/services/types/tiled.py
bouquet/services/types/traefik.py
bouquet/services/types/whoami.py
bouquet/writing.py
rockit_bouquet-0.3.5.dist-info/METADATA
rockit_bouquet-0.3.5.dist-info/WHEEL
rockit_bouquet-0.3.5.dist-info/entry_points.txt
rockit_bouquet-0.3.5.dist-info/licenses/LICENSE
rockit_bouquet-0.3.5.dist-info/RECORD
