Metadata-Version: 2.4
Name: rockit-bouquet
Version: 0.3.5
Summary: A tool for defining and running a set of services for a beamline
License: GNU GPL 3
License-File: LICENSE
Keywords: beamline,bluesky,podman,docker,compose
Author: Devin Burke
Requires-Python: >=3.11
Classifier: Development Status :: 4 - Beta
Classifier: Intended Audience :: Science/Research
Classifier: License :: OSI Approved :: GNU General Public License v3 (GPLv3)
Classifier: License :: Other/Proprietary License
Classifier: Programming Language :: Python :: 3
Classifier: Programming Language :: Python :: 3.11
Classifier: Programming Language :: Python :: 3.12
Classifier: Programming Language :: Python :: 3.13
Classifier: Programming Language :: Python :: 3.14
Classifier: Topic :: Scientific/Engineering
Requires-Dist: cookiecutter (>=2.6.0,<3.0.0)
Requires-Dist: podman-compose (>=1.0.0,<2.0.0)
Requires-Dist: pydantic (>=2.0.0,<3.0.0)
Requires-Dist: requests (>=2.28.0,<3.0.0)
Project-URL: Documentation, https://codebase.helmholtz.cloud/rock-it/wp2/rock-it-starterpack/bouquet/pages
Project-URL: Homepage, https://codebase.helmholtz.cloud/rock-it/wp2/rock-it-starterpack/bouquet
Project-URL: Repository, https://codebase.helmholtz.cloud/rock-it/wp2/rock-it-starterpack/bouquet
